{
  "created_at": "2026-03-06T15:02:11.277791",
  "text": "授業登録をする",
  "duration_minutes": 120,
  "target_list": "other",
  "due": "",
  "category": "admin",
  "priority": "high",
  "schedule_bias_hours": -16,
  "matched_keywords": [
    "授業"
  ],
  "workflow": null,
  "medium_flow": null,
  "split_task_rule": null,
  "timezone": "Asia/Tokyo",
  "snapshot": {
    "start_date": "2026-03-06",
    "end_date": "2026-03-12",
    "warnings": []
  },
  "candidates": [
    {
      "label": "direct",
      "slot_start": "2026-03-07T10:10:00+09:00",
      "slot_end": "2026-03-07T12:10:00+09:00",
      "list_key": "other",
      "score": 1772845800.0,
      "reasons": [
        "fits in free time"
      ],
      "moves": [],
      "segments": []
    },
    {
      "label": "direct",
      "slot_start": "2026-03-08T10:40:00+09:00",
      "slot_end": "2026-03-08T12:40:00+09:00",
      "list_key": "other",
      "score": 1772934000.0,
      "reasons": [
        "fits in free time"
      ],
      "moves": [],
      "segments": []
    },
    {
      "label": "direct",
      "slot_start": "2026-03-08T18:50:00+09:00",
      "slot_end": "2026-03-08T20:50:00+09:00",
      "list_key": "other",
      "score": 1772963400.0,
      "reasons": [
        "fits in free time"
      ],
      "moves": [],
      "segments": []
    }
  ]
}
